CHANGES.rst
CONTRIBUTING.rst
MANIFEST.in
README.rst
setup.py
docs/LICENSE.GPL
docs/LICENSE.txt
plone/__init__.py
plone.app.openid.egg-info/PKG-INFO
plone.app.openid.egg-info/SOURCES.txt
plone.app.openid.egg-info/dependency_links.txt
plone.app.openid.egg-info/entry_points.txt
plone.app.openid.egg-info/namespace_packages.txt
plone.app.openid.egg-info/not-zip-safe
plone.app.openid.egg-info/requires.txt
plone.app.openid.egg-info/top_level.txt
plone/app/__init__.py
plone/app/openid/README.txt
plone/app/openid/__init__.py
plone/app/openid/config.py
plone/app/openid/configure.zcml
plone/app/openid/setuphandlers.py
plone/app/openid/testing.py
plone/app/openid/portlets/__init__.py
plone/app/openid/portlets/configure.zcml
plone/app/openid/portlets/login.pt
plone/app/openid/portlets/login.py
plone/app/openid/profiles/default/metadata.xml
plone/app/openid/profiles/default/portlets.xml
plone/app/openid/profiles/default/skins.xml
plone/app/openid/profiles/uninstall/metadata.xml
plone/app/openid/profiles/uninstall/portlets.xml
plone/app/openid/profiles/uninstall/skins.xml
plone/app/openid/skins/ploneopenid/logged_out.cpt
plone/app/openid/skins/ploneopenid/logged_out.cpt.metadata
plone/app/openid/skins/ploneopenid/login_failed.cpt
plone/app/openid/skins/ploneopenid/login_failed.cpt.metadata
plone/app/openid/skins/ploneopenid/login_form.cpt
plone/app/openid/skins/ploneopenid/login_form.cpt.metadata
plone/app/openid/skins/ploneopenid/openid-icon.gif
plone/app/openid/skins/ploneopenid/openid_login_validate.vpy
plone/app/openid/tests/__init__.py
plone/app/openid/tests/test_view.py